driveshaft/__init__.py
driveshaft-0.0.1.dist-info/WHEEL
driveshaft-0.0.1.dist-info/METADATA
driveshaft-0.0.1.dist-info/RECORD
