Metadata-Version: 2.1
Name: driveshaft
Version: 0.0.1
Summary: Driveshaft is a framework for writing long processing applications in python
Author-email: Alessio Sanfratello <sanfra90@gmail.com>
Classifier: License :: OSI Approved :: MIT License
Project-URL: Home, https://github.com/alesanfra/driveshaft
